handic/__init__.py
handic/handic.py
handic/highlevel.py
handic/paths.py
handic/dicdir/README.md
handic/dicdir/char.bin
handic/dicdir/dicrc
handic/dicdir/matrix.bin
handic/dicdir/mecabrc
handic/dicdir/sys.dic
handic/dicdir/unk.dic
handic/dicdir/version
handic-26.1.4.dist-info/licenses/LICENSE
handic-26.1.4.dist-info/licenses/LICENSE.handic
handic-26.1.4.dist-info/METADATA
handic-26.1.4.dist-info/WHEEL
handic-26.1.4.dist-info/top_level.txt
handic-26.1.4.dist-info/RECORD
