Metadata-Version: 2.4
Name: handic
Version: 26.1.4
Summary: HanDic package for installing via pip.
Author: Yoshinori Sugai
Author-email: okikirmui+github@gmail.com
License: MIT License
Project-URL: Repository, https://github.com/okikirmui/handic-py
Keywords: handic,MeCab,Korean Language,morphological analysis,morphological analysis dictionary,korean text processing
Classifier: License :: OSI Approved :: MIT License
Classifier: Programming Language :: Python
Classifier: Natural Language :: Korean
Classifier: Operating System :: OS Independent
Classifier: Topic :: Text Processing
Requires-Python: >=3.8
License-File: LICENSE
License-File: LICENSE.handic
Dynamic: license-file
